PXITool/PXIControl.py
PXITool/PostProcessing.py
PXITool/PreProcessing.py
PXITool/StoreSetup.py
PXITool/__init__.py
PyMML/PXIControl.py
PyMML/PostProcessing.py
PyMML/PreProcessing.py
PyMML/StoreSetup.py
PyMML/__init__.py
PyMeas/PXIControl.py
PyMeas/PostProcessing.py
PyMeas/PreProcessing.py
PyMeas/StoreSetup.py
PyMeas/__init__.py
PyPXI/PXIControl.py
PyPXI/PostProcessing.py
PyPXI/PreProcessing.py
PyPXI/StoreSetup.py
PyPXI/__init__.py
PyPXIControl/PXIControl.py
PyPXIControl/PostProcessing.py
PyPXIControl/PreProcessing.py
PyPXIControl/StoreSetup.py
PyPXIControl/__init__.py
PXITool-1.0.4.dist-info/LICENSE.txt
PXITool-1.0.4.dist-info/METADATA
PXITool-1.0.4.dist-info/WHEEL
PXITool-1.0.4.dist-info/top_level.txt
PXITool-1.0.4.dist-info/RECORD
