Metadata-Version: 2.1
Name: PXITool
Version: 1.0.4
Summary: Library to cotroll PXI-System
Author: Elias Alizadeh Saboor && Andreas Gschwentner
License: MIT
Requires-Dist: numpy
Requires-Dist: nidmm
Requires-Dist: nidaqmx
Requires-Dist: niswitch
Requires-Dist: h5py
